<?xml version="1.0" encoding="UTF-8"?>
<con:soapui-project id="10aa9bb7-863b-4cc5-a6e5-3a1eba666259" activeEnvironment="Default" name="calci" resourceRoot="" soapui-version="5.6.0" xmlns:con="http://eviware.com/soapui/config"><con:settings/><con:interface xsi:type="con:WsdlInterface" id="f6d75dd0-9a5f-4d9a-b973-b694c92f1f5c" wsaVersion="NONE" name="CalculatorSoap12" type="wsdl" bindingName="{http://tempuri.org/}CalculatorSoap12" soapVersion="1_2" anonymous="optional" definition="http://www.dneonline.com/calculator.asmx?WSDL" xmlns:xsi="http://www.w3.org/2001/XMLSchema-instance"><con:settings/><con:definitionCache/><con:endpoints><con:endpoint>http://www.dneonline.com/calculator.asmx</con:endpoint></con:endpoints><con:operation id="81403a2b-463f-4a30-bc68-32ad8ca95567" isOneWay="false" action="http://tempuri.org/Add" name="Add" bindingOperationName="Add" type="Request-Response" inputName="" receivesAttachments="false" sendsAttachments="false" anonymous="optional"><con:settings/><con:call id="52832758-307c-4010-8e30-ec10cccbda8f" name="Request 1"><con:settings/><con:encoding>UTF-8</con:encoding><con:endpoint>http://www.dneonline.com/calculator.asmx</con:endpoint><con:request><![CDATA[<soap:Envelope xmlns:soap="http://www.w3.org/2003/05/soap-envelope" xmlns:tem="http://tempuri.org/">\r
   <soap:Header/>\r
   <soap:Body>\r
      <tem:Add>\r
         <tem:intA>?</tem:intA>\r
         <tem:intB>?</tem:intB>\r
      </tem:Add>\r
   </soap:Body>\r
</soap:Envelope>]]></con:request><con:wsaConfig mustUnderstand="NONE" version="200508" action="http://tempuri.org/CalculatorSoap/AddRequest"/></con:call></con:operation><con:operation id="008e881b-becb-43f6-9f93-fcc4695be69b" isOneWay="false" action="http://tempuri.org/Divide" name="Divide" bindingOperationName="Divide" type="Request-Response" inputName="" receivesAttachments="false" sendsAttachments="false" anonymous="optional"><con:settings/><con:call id="64e19333-e20c-4a83-b439-309f3e11a2eb" name="Request 1"><con:settings/><con:encoding>UTF-8</con:encoding><con:endpoint>http://www.dneonline.com/calculator.asmx</con:endpoint><con:request><![CDATA[<soap:Envelope xmlns:soap="http://www.w3.org/2003/05/soap-envelope" xmlns:tem="http://tempuri.org/">\r
   <soap:Header/>\r
   <soap:Body>\r
      <tem:Divide>\r
         <tem:intA>?</tem:intA>\r
         <tem:intB>?</tem:intB>\r
      </tem:Divide>\r
   </soap:Body>\r
</soap:Envelope>]]></con:request><con:wsaConfig mustUnderstand="NONE" version="200508" action="http://tempuri.org/CalculatorSoap/DivideRequest"/></con:call></con:operation><con:operation id="0236bc2d-b209-4537-9f2b-001050c90a5b" isOneWay="false" action="http://tempuri.org/Multiply" name="Multiply" bindingOperationName="Multiply" type="Request-Response" inputName="" receivesAttachments="false" sendsAttachments="false" anonymous="optional"><con:settings/><con:call id="6b393e13-bdbd-4c37-b659-23aa00912324" name="Request 1"><con:settings/><con:encoding>UTF-8</con:encoding><con:endpoint>http://www.dneonline.com/calculator.asmx</con:endpoint><con:request><![CDATA[<soap:Envelope xmlns:soap="http://www.w3.org/2003/05/soap-envelope" xmlns:tem="http://tempuri.org/">\r
   <soap:Header/>\r
   <soap:Body>\r
      <tem:Multiply>\r
         <tem:intA>?</tem:intA>\r
         <tem:intB>?</tem:intB>\r
      </tem:Multiply>\r
   </soap:Body>\r
</soap:Envelope>]]></con:request><con:wsaConfig mustUnderstand="NONE" version="200508" action="http://tempuri.org/CalculatorSoap/MultiplyRequest"/></con:call></con:operation><con:operation id="510c2a63-cf2a-4063-8a5b-b118ddf74f3d" isOneWay="false" action="http://tempuri.org/Subtract" name="Subtract" bindingOperationName="Subtract" type="Request-Response" inputName="" receivesAttachments="false" sendsAttachments="false" anonymous="optional"><con:settings/><con:call id="40e46795-8e3d-4115-bdaa-b9612ddd922a" name="Request 1"><con:settings/><con:encoding>UTF-8</con:encoding><con:endpoint>http://www.dneonline.com/calculator.asmx</con:endpoint><con:request><![CDATA[<soap:Envelope xmlns:soap="http://www.w3.org/2003/05/soap-envelope" xmlns:tem="http://tempuri.org/">\r
   <soap:Header/>\r
   <soap:Body>\r
      <tem:Subtract>\r
         <tem:intA>?</tem:intA>\r
         <tem:intB>?</tem:intB>\r
      </tem:Subtract>\r
   </soap:Body>\r
</soap:Envelope>]]></con:request><con:wsaConfig mustUnderstand="NONE" version="200508" action="http://tempuri.org/CalculatorSoap/SubtractRequest"/></con:call></con:operation></con:interface><con:interface xsi:type="con:WsdlInterface" id="80f8eff2-6f1c-4f0f-9701-b2443a5569bb" wsaVersion="NONE" name="CalculatorSoap" type="wsdl" bindingName="{http://tempuri.org/}CalculatorSoap" soapVersion="1_1" anonymous="optional" definition="http://www.dneonline.com/calculator.asmx?WSDL" xmlns:xsi="http://www.w3.org/2001/XMLSchema-instance"><con:settings/><con:definitionCache type="TEXT" rootPart="http://www.dneonline.com/calculator.asmx?WSDL"><con:part><con:url>http://www.dneonline.com/calculator.asmx?WSDL</con:url><con:content><![CDATA[<wsdl:definitions targetNamespace="http://tempuri.org/" xmlns:soap="http://schemas.xmlsoap.org/wsdl/soap/" xmlns:tm="http://microsoft.com/wsdl/mime/textMatching/" xmlns:soapenc="http://schemas.xmlsoap.org/soap/encoding/" xmlns:mime="http://schemas.xmlsoap.org/wsdl/mime/" xmlns:tns="http://tempuri.org/" xmlns:s="http://www.w3.org/2001/XMLSchema" xmlns:soap12="http://schemas.xmlsoap.org/wsdl/soap12/" xmlns:http="http://schemas.xmlsoap.org/wsdl/http/" xmlns:wsdl="http://schemas.xmlsoap.org/wsdl/">
  <wsdl:types>
    <s:schema elementFormDefault="qualified" targetNamespace="http://tempuri.org/">
      <s:element name="Add">
        <s:complexType>
          <s:sequence>
            <s:element minOccurs="1" maxOccurs="1" name="intA" type="s:int"/>
            <s:element minOccurs="1" maxOccurs="1" name="intB" type="s:int"/>
          </s:sequence>
        </s:complexType>
      </s:element>
      <s:element name="AddResponse">
        <s:complexType>
          <s:sequence>
            <s:element minOccurs="1" maxOccurs="1" name="AddResult" type="s:int"/>
          </s:sequence>
        </s:complexType>
      </s:element>
      <s:element name="Subtract">
        <s:complexType>
          <s:sequence>
            <s:element minOccurs="1" maxOccurs="1" name="intA" type="s:int"/>
            <s:element minOccurs="1" maxOccurs="1" name="intB" type="s:int"/>
          </s:sequence>
        </s:complexType>
      </s:element>
      <s:element name="SubtractResponse">
        <s:complexType>
          <s:sequence>
            <s:element minOccurs="1" maxOccurs="1" name="SubtractResult" type="s:int"/>
          </s:sequence>
        </s:complexType>
      </s:element>
      <s:element name="Multiply">
        <s:complexType>
          <s:sequence>
            <s:element minOccurs="1" maxOccurs="1" name="intA" type="s:int"/>
            <s:element minOccurs="1" maxOccurs="1" name="intB" type="s:int"/>
          </s:sequence>
        </s:complexType>
      </s:element>
      <s:element name="MultiplyResponse">
        <s:complexType>
          <s:sequence>
            <s:element minOccurs="1" maxOccurs="1" name="MultiplyResult" type="s:int"/>
          </s:sequence>
        </s:complexType>
      </s:element>
      <s:element name="Divide">
        <s:complexType>
          <s:sequence>
            <s:element minOccurs="1" maxOccurs="1" name="intA" type="s:int"/>
            <s:element minOccurs="1" maxOccurs="1" name="intB" type="s:int"/>
          </s:sequence>
        </s:complexType>
      </s:element>
      <s:element name="DivideResponse">
        <s:complexType>
          <s:sequence>
            <s:element minOccurs="1" maxOccurs="1" name="DivideResult" type="s:int"/>
          </s:sequence>
        </s:complexType>
      </s:element>
    </s:schema>
  </wsdl:types>
  <wsdl:message name="AddSoapIn">
    <wsdl:part name="parameters" element="tns:Add"/>
  </wsdl:message>
  <wsdl:message name="AddSoapOut">
    <wsdl:part name="parameters" element="tns:AddResponse"/>
  </wsdl:message>
  <wsdl:message name="SubtractSoapIn">
    <wsdl:part name="parameters" element="tns:Subtract"/>
  </wsdl:message>
  <wsdl:message name="SubtractSoapOut">
    <wsdl:part name="parameters" element="tns:SubtractResponse"/>
  </wsdl:message>
  <wsdl:message name="MultiplySoapIn">
    <wsdl:part name="parameters" element="tns:Multiply"/>
  </wsdl:message>
  <wsdl:message name="MultiplySoapOut">
    <wsdl:part name="parameters" element="tns:MultiplyResponse"/>
  </wsdl:message>
  <wsdl:message name="DivideSoapIn">
    <wsdl:part name="parameters" element="tns:Divide"/>
  </wsdl:message>
  <wsdl:message name="DivideSoapOut">
    <wsdl:part name="parameters" element="tns:DivideResponse"/>
  </wsdl:message>
  <wsdl:portType name="CalculatorSoap">
    <wsdl:operation name="Add">
      <wsdl:documentation>Adds two integers. This is a test WebService. ©DNE Online</wsdl:documentation>
      <wsdl:input message="tns:AddSoapIn"/>
      <wsdl:output message="tns:AddSoapOut"/>
    </wsdl:operation>
    <wsdl:operation name="Subtract">
      <wsdl:input message="tns:SubtractSoapIn"/>
      <wsdl:output message="tns:SubtractSoapOut"/>
    </wsdl:operation>
    <wsdl:operation name="Multiply">
      <wsdl:input message="tns:MultiplySoapIn"/>
      <wsdl:output message="tns:MultiplySoapOut"/>
    </wsdl:operation>
    <wsdl:operation name="Divide">
      <wsdl:input message="tns:DivideSoapIn"/>
      <wsdl:output message="tns:DivideSoapOut"/>
    </wsdl:operation>
  </wsdl:portType>
  <wsdl:binding name="CalculatorSoap" type="tns:CalculatorSoap">
    <soap:binding transport="http://schemas.xmlsoap.org/soap/http"/>
    <wsdl:operation name="Add">
      <soap:operation soapAction="http://tempuri.org/Add" style="document"/>
      <wsdl:input>
        <soap:body use="literal"/>
      </wsdl:input>
      <wsdl:output>
        <soap:body use="literal"/>
      </wsdl:output>
    </wsdl:operation>
    <wsdl:operation name="Subtract">
      <soap:operation soapAction="http://tempuri.org/Subtract" style="document"/>
      <wsdl:input>
        <soap:body use="literal"/>
      </wsdl:input>
      <wsdl:output>
        <soap:body use="literal"/>
      </wsdl:output>
    </wsdl:operation>
    <wsdl:operation name="Multiply">
      <soap:operation soapAction="http://tempuri.org/Multiply" style="document"/>
      <wsdl:input>
        <soap:body use="literal"/>
      </wsdl:input>
      <wsdl:output>
        <soap:body use="literal"/>
      </wsdl:output>
    </wsdl:operation>
    <wsdl:operation name="Divide">
      <soap:operation soapAction="http://tempuri.org/Divide" style="document"/>
      <wsdl:input>
        <soap:body use="literal"/>
      </wsdl:input>
      <wsdl:output>
        <soap:body use="literal"/>
      </wsdl:output>
    </wsdl:operation>
  </wsdl:binding>
  <wsdl:binding name="CalculatorSoap12" type="tns:CalculatorSoap">
    <soap12:binding transport="http://schemas.xmlsoap.org/soap/http"/>
    <wsdl:operation name="Add">
      <soap12:operation soapAction="http://tempuri.org/Add" style="document"/>
      <wsdl:input>
        <soap12:body use="literal"/>
      </wsdl:input>
      <wsdl:output>
        <soap12:body use="literal"/>
      </wsdl:output>
    </wsdl:operation>
    <wsdl:operation name="Subtract">
      <soap12:operation soapAction="http://tempuri.org/Subtract" style="document"/>
      <wsdl:input>
        <soap12:body use="literal"/>
      </wsdl:input>
      <wsdl:output>
        <soap12:body use="literal"/>
      </wsdl:output>
    </wsdl:operation>
    <wsdl:operation name="Multiply">
      <soap12:operation soapAction="http://tempuri.org/Multiply" style="document"/>
      <wsdl:input>
        <soap12:body use="literal"/>
      </wsdl:input>
      <wsdl:output>
        <soap12:body use="literal"/>
      </wsdl:output>
    </wsdl:operation>
    <wsdl:operation name="Divide">
      <soap12:operation soapAction="http://tempuri.org/Divide" style="document"/>
      <wsdl:input>
        <soap12:body use="literal"/>
      </wsdl:input>
      <wsdl:output>
        <soap12:body use="literal"/>
      </wsdl:output>
    </wsdl:operation>
  </wsdl:binding>
  <wsdl:service name="Calculator">
    <wsdl:port name="CalculatorSoap" binding="tns:CalculatorSoap">
      <soap:address location="http://www.dneonline.com/calculator.asmx"/>
    </wsdl:port>
    <wsdl:port name="CalculatorSoap12" binding="tns:CalculatorSoap12">
      <soap12:address location="http://www.dneonline.com/calculator.asmx"/>
    </wsdl:port>
  </wsdl:service>
</wsdl:definitions>]]></con:content><con:type>http://schemas.xmlsoap.org/wsdl/</con:type></con:part></con:definitionCache><con:endpoints><con:endpoint>http://www.dneonline.com/calculator.asmx</con:endpoint></con:endpoints><con:operation id="f802ab49-4815-4897-b8c8-7aa12fadd118" isOneWay="false" action="http://tempuri.org/Add" name="Add" bindingOperationName="Add" type="Request-Response" inputName="" receivesAttachments="false" sendsAttachments="false" anonymous="optional"><con:settings/><con:call id="b7fe8c69-29c3-4298-8454-a24606492c44" name="Request 1"><con:settings><con:setting id="com.eviware.soapui.impl.wsdl.WsdlRequest@request-headers">&lt;xml-fragment/></con:setting></con:settings><con:encoding>UTF-8</con:encoding><con:endpoint>http://www.dneonline.com/calculator.asmx</con:endpoint><con:request><![CDATA[<soapenv:Envelope xmlns:soapenv="http://schemas.xmlsoap.org/soap/envelope/" xmlns:tem="http://tempuri.org/">\r
   <soapenv:Header/>\r
   <soapenv:Body>\r
      <tem:Add>\r
         <tem:intA>18</tem:intA>\r
         <tem:intB>0</tem:intB>\r
      </tem:Add>\r
   </soapenv:Body>\r
</soapenv:Envelope>]]></con:request><con:credentials><con:authType>No Authorization</con:authType></con:credentials><con:jmsConfig JMSDeliveryMode="PERSISTENT"/><con:jmsPropertyConfig/><con:wsaConfig mustUnderstand="NONE" version="200508" action="http://tempuri.org/Add"/><con:wsrmConfig version="1.2"/></con:call></con:operation><con:operation id="195c595b-36f2-44e9-b3c3-a8b5ecc475e4" isOneWay="false" action="http://tempuri.org/Divide" name="Divide" bindingOperationName="Divide" type="Request-Response" inputName="" receivesAttachments="false" sendsAttachments="false" anonymous="optional"><con:settings/><con:call id="99f515d8-87e4-4705-9e82-5238fff9be8d" name="Request 1"><con:settings/><con:encoding>UTF-8</con:encoding><con:endpoint>http://www.dneonline.com/calculator.asmx</con:endpoint><con:request><![CDATA[<soapenv:Envelope xmlns:soapenv="http://schemas.xmlsoap.org/soap/envelope/" xmlns:tem="http://tempuri.org/">\r
   <soapenv:Header/>\r
   <soapenv:Body>\r
      <tem:Divide>\r
         <tem:intA>?</tem:intA>\r
         <tem:intB>?</tem:intB>\r
      </tem:Divide>\r
   </soapenv:Body>\r
</soapenv:Envelope>]]></con:request><con:wsaConfig mustUnderstand="NONE" version="200508" action="http://tempuri.org/Divide"/></con:call></con:operation><con:operation id="310cc677-bd3a-4490-931c-2df0ea1b447a" isOneWay="false" action="http://tempuri.org/Multiply" name="Multiply" bindingOperationName="Multiply" type="Request-Response" inputName="" receivesAttachments="false" sendsAttachments="false" anonymous="optional"><con:settings/><con:call id="4614d1c7-329b-43b3-8f39-da416634bb48" name="Request 1"><con:settings/><con:encoding>UTF-8</con:encoding><con:endpoint>http://www.dneonline.com/calculator.asmx</con:endpoint><con:request><![CDATA[<soapenv:Envelope xmlns:soapenv="http://schemas.xmlsoap.org/soap/envelope/" xmlns:tem="http://tempuri.org/">\r
   <soapenv:Header/>\r
   <soapenv:Body>\r
      <tem:Multiply>\r
         <tem:intA>?</tem:intA>\r
         <tem:intB>?</tem:intB>\r
      </tem:Multiply>\r
   </soapenv:Body>\r
</soapenv:Envelope>]]></con:request><con:wsaConfig mustUnderstand="NONE" version="200508" action="http://tempuri.org/Multiply"/></con:call></con:operation><con:operation id="dc74d5d8-a305-47dd-9978-7d1fe1090894" isOneWay="false" action="http://tempuri.org/Subtract" name="Subtract" bindingOperationName="Subtract" type="Request-Response" inputName="" receivesAttachments="false" sendsAttachments="false" anonymous="optional"><con:settings/><con:call id="7459341a-ac45-4030-a7d7-2e03ef17c2cc" name="Request 1"><con:settings/><con:encoding>UTF-8</con:encoding><con:endpoint>http://www.dneonline.com/calculator.asmx</con:endpoint><con:request><![CDATA[<soapenv:Envelope xmlns:soapenv="http://schemas.xmlsoap.org/soap/envelope/" xmlns:tem="http://tempuri.org/">\r
   <soapenv:Header/>\r
   <soapenv:Body>\r
      <tem:Subtract>\r
         <tem:intA>?</tem:intA>\r
         <tem:intB>?</tem:intB>\r
      </tem:Subtract>\r
   </soapenv:Body>\r
</soapenv:Envelope>]]></con:request><con:wsaConfig mustUnderstand="NONE" version="200508" action="http://tempuri.org/Subtract"/></con:call></con:operation></con:interface><con:testSuite id="3d8f6c62-751c-4246-a265-e96f95ba5c73" name="TestSuite 1"><con:settings/><con:runType>SEQUENTIAL</con:runType><con:testCase id="f70aca24-eca1-4bc5-93b4-e471c9030e33" failOnError="true" failTestCaseOnErrors="true" keepSession="false" maxResults="0" name="TestCase 1" searchProperties="true"><con:settings/><con:testStep type="request" name="SOAP Request" id="992ab656-eecd-4f62-b396-9f01bdfaf632"><con:settings/><con:config xsi:type="con:RequestStep" xmlns:xsi="http://www.w3.org/2001/XMLSchema-instance"><con:interface>CalculatorSoap12</con:interface><con:operation>Add</con:operation><con:request name="SOAP Request" id="60c25a2a-bf39-4834-8c21-f38f590f36e6"><con:settings><con:setting id="com.eviware.soapui.impl.wsdl.WsdlRequest@request-headers">&lt;xml-fragment/></con:setting></con:settings><con:encoding>UTF-8</con:encoding><con:endpoint>http://www.dneonline.com/calculator.asmx</con:endpoint><con:request><![CDATA[<soap:Envelope xmlns:soap="http://www.w3.org/2003/05/soap-envelope" xmlns:tem="http://tempuri.org/">\r
   <soap:Header/>\r
   <soap:Body>\r
      <tem:Add>\r
         <tem:intA>5</tem:intA>\r
         <tem:intB>5</tem:intB>\r
      </tem:Add>\r
   </soap:Body>\r
</soap:Envelope>]]></con:request><con:assertion type="Simple Contains" id="d290f6de-05df-41e9-a2c3-a12926d5b616" name="Contains"><con:configuration><token>10</token><ignoreCase>false</ignoreCase><useRegEx>false</useRegEx></con:configuration></con:assertion><con:assertion type="Simple NotContains" id="55c2d996-5365-48f7-9687-1d6a99914d03" name="Not Contains"><con:configuration><token>20
</token><ignoreCase>false</ignoreCase><useRegEx>false</useRegEx></con:configuration></con:assertion><con:assertion type="XPath Match" id="562ae0c6-8f17-4a1b-8e3d-7d35750477ac" name="XPath Match"><con:configuration/></con:assertion><con:assertion type="XPath Match" id="dbf91f51-0e59-499d-be37-7752ecd56f67" name="XPath Match 1"><con:configuration><path>declare namespace ns1='http://tempuri.org/';
declare namespace soap='http://www.w3.org/2003/05/soap-envelope';
//ns1:AddResult</path><content>60</content><allowWildcards>false</allowWildcards><ignoreNamspaceDifferences>false</ignoreNamspaceDifferences><ignoreComments>false</ignoreComments></con:configuration></con:assertion><con:credentials><con:authType>No Authorization</con:authType></con:credentials><con:jmsConfig JMSDeliveryMode="PERSISTENT"/><con:jmsPropertyConfig/><con:wsaConfig mustUnderstand="NONE" version="200508"/><con:wsrmConfig version="1.2"/></con:request></con:config></con:testStep><con:properties/></con:testCase><con:properties/></con:testSuite><con:properties/><con:wssContainer/><con:oAuth2ProfileContainer/><con:oAuth1ProfileContainer/></con:soapui-project>